{
  "account": {
    "portfolioValue": 50679.14,
    "cash": -63155.94,
    "buyingPower": 40621.25,
    "equity": 50679.14,
    "longMarketValue": 113835.08,
    "shortMarketValue": 0,
    "pnl": -49320.86,
    "pnlPct": -49.320859999999996
  },
  "positions": [
    {
      "symbol": "ADBE",
      "qty": 6.172307439,
      "side": "long",
      "avgEntry": 243.020947,
      "currentPrice": 239.43,
      "marketValue": 1477.83557,
      "unrealizedPnl": -22.164429,
      "unrealizedPnlPct": -1.478,
      "change": -3.315
    },
    {
      "symbol": "ADPT",
      "qty": 50,
      "side": "long",
      "avgEntry": 13.29,
      "currentPrice": 13.71,
      "marketValue": 685.5,
      "unrealizedPnl": 21,
      "unrealizedPnlPct": 3.16,
      "change": 0.366
    },
    {
      "symbol": "AHCO",
      "qty": 419.333240162,
      "side": "long",
      "avgEntry": 10.817554,
      "currentPrice": 11.24,
      "marketValue": 4713.305619,
      "unrealizedPnl": 177.14565,
      "unrealizedPnlPct": 3.9050000000000002,
      "change": 8.39
    },
    {
      "symbol": "AIRS",
      "qty": 500,
      "side": "long",
      "avgEntry": 2.86,
      "currentPrice": 2.87,
      "marketValue": 1435,
      "unrealizedPnl": 5,
      "unrealizedPnlPct": 0.35000000000000003,
      "change": 3.237
    },
    {
      "symbol": "AISP",
      "qty": 1000,
      "side": "long",
      "avgEntry": 2.445,
      "currentPrice": 2.29,
      "marketValue": 2290,
      "unrealizedPnl": -155,
      "unrealizedPnlPct": -6.339,
      "change": -3.782
    },
    {
      "symbol": "AMKR",
      "qty": 11.508203894,
      "side": "long",
      "avgEntry": 45.71,
      "currentPrice": 49.0513,
      "marketValue": 564.492362,
      "unrealizedPnl": 38.452362,
      "unrealizedPnlPct": 7.31,
      "change": 6.356000000000001
    },
    {
      "symbol": "AMR",
      "qty": 11.744891116,
      "side": "long",
      "avgEntry": 199.868959,
      "currentPrice": 218.45,
      "marketValue": 2565.671464,
      "unrealizedPnl": 218.232303,
      "unrealizedPnlPct": 9.297,
      "change": 8.882
    },
    {
      "symbol": "APG",
      "qty": 25.902345619,
      "side": "long",
      "avgEntry": 41.78,
      "currentPrice": 42.165,
      "marketValue": 1092.172403,
      "unrealizedPnl": 9.972403,
      "unrealizedPnlPct": 0.9209999999999999,
      "change": 1.7000000000000002
    },
    {
      "symbol": "AVBC",
      "qty": 75,
      "side": "long",
      "avgEntry": 18.97,
      "currentPrice": 19.38,
      "marketValue": 1453.5,
      "unrealizedPnl": 30.75,
      "unrealizedPnlPct": 2.161,
      "change": 0.155
    },
    {
      "symbol": "AVGO",
      "qty": 8.274903523,
      "side": "long",
      "avgEntry": 318.686495,
      "currentPrice": 317.76,
      "marketValue": 2629.433343,
      "unrealizedPnl": -7.666657,
      "unrealizedPnlPct": -0.291,
      "change": -1.473
    },
    {
      "symbol": "AVO",
      "qty": 159.872102318,
      "side": "long",
      "avgEntry": 12.51,
      "currentPrice": 13.065,
      "marketValue": 2088.729017,
      "unrealizedPnl": 88.729017,
      "unrealizedPnlPct": 4.436,
      "change": 3.199
    },
    {
      "symbol": "BCIC",
      "qty": 204.638472032,
      "side": "long",
      "avgEntry": 7.33,
      "currentPrice": 7.29,
      "marketValue": 1491.814461,
      "unrealizedPnl": -8.185539,
      "unrealizedPnlPct": -0.5459999999999999,
      "change": 0.97
    },
    {
      "symbol": "CLIR",
      "qty": 6,
      "side": "long",
      "avgEntry": 3.49,
      "currentPrice": 3.68,
      "marketValue": 22.08,
      "unrealizedPnl": 1.14,
      "unrealizedPnlPct": 5.444,
      "change": 2.222
    },
    {
      "symbol": "CME",
      "qty": 15,
      "side": "long",
      "avgEntry": 309.43,
      "currentPrice": 305,
      "marketValue": 4575,
      "unrealizedPnl": -66.45,
      "unrealizedPnlPct": -1.432,
      "change": -0.509
    },
    {
      "symbol": "CRS",
      "qty": 0.496037745,
      "side": "long",
      "avgEntry": 377.26,
      "currentPrice": 397.9175,
      "marketValue": 197.382099,
      "unrealizedPnl": 10.246899,
      "unrealizedPnlPct": 5.476,
      "change": 6.626
    },
    {
      "symbol": "CRTO",
      "qty": 0.00356408,
      "side": "long",
      "avgEntry": 18.408358,
      "currentPrice": 17.45,
      "marketValue": 0.062193,
      "unrealizedPnl": -0.003416,
      "unrealizedPnlPct": -5.207,
      "change": 0.22999999999999998
    },
    {
      "symbol": "CULP",
      "qty": 640,
      "side": "long",
      "avgEntry": 2.92,
      "currentPrice": 2.85,
      "marketValue": 1824,
      "unrealizedPnl": -44.8,
      "unrealizedPnlPct": -2.3970000000000002,
      "change": 1.064
    },
    {
      "symbol": "DNTH",
      "qty": 23,
      "side": "long",
      "avgEntry": 79.11,
      "currentPrice": 78.39,
      "marketValue": 1802.97,
      "unrealizedPnl": -16.56,
      "unrealizedPnlPct": -0.91,
      "change": -1.172
    },
    {
      "symbol": "EML",
      "qty": 120,
      "side": "long",
      "avgEntry": 20.51,
      "currentPrice": 20.76,
      "marketValue": 2491.2,
      "unrealizedPnl": 30,
      "unrealizedPnlPct": 1.2189999999999999,
      "change": -1.8900000000000001
    },
    {
      "symbol": "ESOA",
      "qty": 108.105187319,
      "side": "long",
      "avgEntry": 13.875375,
      "currentPrice": 14.4,
      "marketValue": 1556.714697,
      "unrealizedPnl": 56.714684,
      "unrealizedPnlPct": 3.781,
      "change": 4.197
    },
    {
      "symbol": "FCFS",
      "qty": 10.620682544,
      "side": "long",
      "avgEntry": 193.98,
      "currentPrice": 194.71,
      "marketValue": 2067.953098,
      "unrealizedPnl": 7.753098,
      "unrealizedPnlPct": 0.376,
      "change": 0.563
    },
    {
      "symbol": "FFIN",
      "qty": 4,
      "side": "long",
      "avgEntry": 29.37,
      "currentPrice": 29.84,
      "marketValue": 119.36,
      "unrealizedPnl": 1.88,
      "unrealizedPnlPct": 1.6,
      "change": 1.016
    },
    {
      "symbol": "FIVE",
      "qty": 5,
      "side": "long",
      "avgEntry": 229.36,
      "currentPrice": 230.46,
      "marketValue": 1152.3,
      "unrealizedPnl": 5.5,
      "unrealizedPnlPct": 0.48,
      "change": -0.017
    },
    {
      "symbol": "FOSL",
      "qty": 241.545893719,
      "side": "long",
      "avgEntry": 4.14,
      "currentPrice": 4.035,
      "marketValue": 974.637681,
      "unrealizedPnl": -25.362319,
      "unrealizedPnlPct": -2.536,
      "change": -0.124
    },
    {
      "symbol": "FOX",
      "qty": 64,
      "side": "long",
      "avgEntry": 52.5704,
      "currentPrice": 52.74,
      "marketValue": 3375.36,
      "unrealizedPnl": 10.8544,
      "unrealizedPnlPct": 0.32299999999999995,
      "change": 2.15
    },
    {
      "symbol": "FSUN",
      "qty": 0.028188056,
      "side": "long",
      "avgEntry": 34.693749,
      "currentPrice": 36.26,
      "marketValue": 1.022099,
      "unrealizedPnl": 0.04415,
      "unrealizedPnlPct": 4.515000000000001,
      "change": -0.33
    },
    {
      "symbol": "GO",
      "qty": 10.102040816,
      "side": "long",
      "avgEntry": 6.227368,
      "currentPrice": 6.765,
      "marketValue": 68.340306,
      "unrealizedPnl": 5.43118,
      "unrealizedPnlPct": 8.633000000000001,
      "change": 4.884
    },
    {
      "symbol": "HBIO",
      "qty": 0.169621567,
      "side": "long",
      "avgEntry": 4.89,
      "currentPrice": 5.16,
      "marketValue": 0.875247,
      "unrealizedPnl": 0.045798,
      "unrealizedPnlPct": 5.521,
      "change": -3.3709999999999996
    },
    {
      "symbol": "IBIO",
      "qty": 436.681222708,
      "side": "long",
      "avgEntry": 2.29,
      "currentPrice": 2.1,
      "marketValue": 917.030568,
      "unrealizedPnl": -82.969432,
      "unrealizedPnlPct": -8.297,
      "change": -4.977
    },
    {
      "symbol": "KLTR",
      "qty": 1896.594772558,
      "side": "long",
      "avgEntry": 1.22364,
      "currentPrice": 1.225,
      "marketValue": 2323.328596,
      "unrealizedPnl": 2.579369,
      "unrealizedPnlPct": 0.11100000000000002,
      "change": 0.41000000000000003
    },
    {
      "symbol": "KR",
      "qty": 0.20369874,
      "side": "long",
      "avgEntry": 73.34,
      "currentPrice": 73.09,
      "marketValue": 14.888341,
      "unrealizedPnl": -0.050925,
      "unrealizedPnlPct": -0.34099999999999997,
      "change": 0.536
    },
    {
      "symbol": "KYN",
      "qty": 107.142857142,
      "side": "long",
      "avgEntry": 14,
      "currentPrice": 14.32,
      "marketValue": 1534.285714,
      "unrealizedPnl": 34.285714,
      "unrealizedPnlPct": 2.286,
      "change": 2.213
    },
    {
      "symbol": "LAC",
      "qty": 500,
      "side": "long",
      "avgEntry": 3.96,
      "currentPrice": 4,
      "marketValue": 2000,
      "unrealizedPnl": 20,
      "unrealizedPnlPct": 1.01,
      "change": 1.5230000000000001
    },
    {
      "symbol": "LRN",
      "qty": 0.170405278,
      "side": "long",
      "avgEntry": 84.888913,
      "currentPrice": 87.145,
      "marketValue": 14.849968,
      "unrealizedPnl": 0.384449,
      "unrealizedPnlPct": 2.658,
      "change": -0.212
    },
    {
      "symbol": "MKTW",
      "qty": 68,
      "side": "long",
      "avgEntry": 15.49,
      "currentPrice": 16.14,
      "marketValue": 1097.52,
      "unrealizedPnl": 44.2,
      "unrealizedPnlPct": 4.196,
      "change": 11.081000000000001
    },
    {
      "symbol": "MPWR",
      "qty": 2.813678227,
      "side": "long",
      "avgEntry": 1066.22,
      "currentPrice": 1081.38,
      "marketValue": 3042.655361,
      "unrealizedPnl": 42.655362,
      "unrealizedPnlPct": 1.422,
      "change": 0.46699999999999997
    },
    {
      "symbol": "NBTB",
      "qty": 18,
      "side": "long",
      "avgEntry": 41.41,
      "currentPrice": 42.51,
      "marketValue": 765.18,
      "unrealizedPnl": 19.8,
      "unrealizedPnlPct": 2.656,
      "change": 1.238
    },
    {
      "symbol": "NFBK",
      "qty": 83,
      "side": "long",
      "avgEntry": 13.225181,
      "currentPrice": 13.56,
      "marketValue": 1125.48,
      "unrealizedPnl": 27.789977,
      "unrealizedPnlPct": 2.532,
      "change": 0.5930000000000001
    },
    {
      "symbol": "NP",
      "qty": 0.125,
      "side": "long",
      "avgEntry": 22.356,
      "currentPrice": 22.11,
      "marketValue": 2.76375,
      "unrealizedPnl": -0.03075,
      "unrealizedPnlPct": -1.0999999999999999,
      "change": 0.729
    },
    {
      "symbol": "NTAP",
      "qty": 29.254022428,
      "side": "long",
      "avgEntry": 102.55,
      "currentPrice": 102.99,
      "marketValue": 3012.87177,
      "unrealizedPnl": 12.87177,
      "unrealizedPnlPct": 0.42900000000000005,
      "change": 1.6680000000000001
    },
    {
      "symbol": "NVDA",
      "qty": 2,
      "side": "long",
      "avgEntry": 177.625,
      "currentPrice": 174.9,
      "marketValue": 349.8,
      "unrealizedPnl": -5.45,
      "unrealizedPnlPct": -1.534,
      "change": -0.42100000000000004
    },
    {
      "symbol": "NVDA260327C00190000",
      "qty": 1,
      "side": "long",
      "avgEntry": 0.07,
      "currentPrice": 0.03,
      "marketValue": 3,
      "unrealizedPnl": -4,
      "unrealizedPnlPct": -57.143,
      "change": -50
    },
    {
      "symbol": "NVDA260410C00180000",
      "qty": 8,
      "side": "long",
      "avgEntry": 3.71875,
      "currentPrice": 3,
      "marketValue": 2400,
      "unrealizedPnl": -575,
      "unrealizedPnlPct": -19.328,
      "change": -15.493000000000002
    },
    {
      "symbol": "OCSL",
      "qty": 53.050397877,
      "side": "long",
      "avgEntry": 11.31,
      "currentPrice": 11.2,
      "marketValue": 594.164456,
      "unrealizedPnl": -5.835544,
      "unrealizedPnlPct": -0.9730000000000001,
      "change": -1.2349999999999999
    },
    {
      "symbol": "OSUR",
      "qty": 1672.67008488,
      "side": "long",
      "avgEntry": 3.063578,
      "currentPrice": 3.115,
      "marketValue": 5210.367314,
      "unrealizedPnl": 86.012041,
      "unrealizedPnlPct": 1.678,
      "change": 1.1360000000000001
    },
    {
      "symbol": "PHR",
      "qty": 0.332899792,
      "side": "long",
      "avgEntry": 12.008585,
      "currentPrice": 11.19,
      "marketValue": 3.725149,
      "unrealizedPnl": -0.272506,
      "unrealizedPnlPct": -6.816999999999999,
      "change": -5.169
    },
    {
      "symbol": "PICS",
      "qty": 400,
      "side": "long",
      "avgEntry": 11.515,
      "currentPrice": 11.44,
      "marketValue": 4576,
      "unrealizedPnl": -30,
      "unrealizedPnlPct": -0.651,
      "change": -3.46
    },
    {
      "symbol": "SBSW",
      "qty": 377.316767735,
      "side": "long",
      "avgEntry": 11.179433,
      "currentPrice": 11.37,
      "marketValue": 4290.091649,
      "unrealizedPnl": 71.904124,
      "unrealizedPnlPct": 1.7049999999999998,
      "change": 0.265
    },
    {
      "symbol": "SENS",
      "qty": 0.19197702,
      "side": "long",
      "avgEntry": 6.331159,
      "currentPrice": 6.725,
      "marketValue": 1.291045,
      "unrealizedPnl": 0.075608,
      "unrealizedPnlPct": 6.221,
      "change": 1.5859999999999999
    },
    {
      "symbol": "SFM",
      "qty": 15,
      "side": "long",
      "avgEntry": 79.46,
      "currentPrice": 78.815,
      "marketValue": 1182.225,
      "unrealizedPnl": -9.675,
      "unrealizedPnlPct": -0.812,
      "change": -0.108
    },
    {
      "symbol": "SLRC",
      "qty": 200,
      "side": "long",
      "avgEntry": 14.35,
      "currentPrice": 14.255,
      "marketValue": 2851,
      "unrealizedPnl": -19,
      "unrealizedPnlPct": -0.662,
      "change": -1.0070000000000001
    },
    {
      "symbol": "SRBK",
      "qty": 60,
      "side": "long",
      "avgEntry": 16.67,
      "currentPrice": 17.09,
      "marketValue": 1025.4,
      "unrealizedPnl": 25.2,
      "unrealizedPnlPct": 2.519,
      "change": 0.411
    },
    {
      "symbol": "STIM",
      "qty": 79,
      "side": "long",
      "avgEntry": 1.577143,
      "currentPrice": 1.465,
      "marketValue": 115.735,
      "unrealizedPnl": -8.859297,
      "unrealizedPnlPct": -7.111000000000001,
      "change": -8.437999999999999
    },
    {
      "symbol": "STIM260417C00002500",
      "qty": 15,
      "side": "long",
      "avgEntry": 0.35,
      "currentPrice": 0,
      "marketValue": 0,
      "unrealizedPnl": -525,
      "unrealizedPnlPct": -100,
      "change": null
    },
    {
      "symbol": "TOI",
      "qty": 150,
      "side": "long",
      "avgEntry": 3.15,
      "currentPrice": 3.12,
      "marketValue": 468,
      "unrealizedPnl": -4.5,
      "unrealizedPnlPct": -0.9520000000000001,
      "change": -2.804
    },
    {
      "symbol": "TPL",
      "qty": 1.89389635,
      "side": "long",
      "avgEntry": 528.012,
      "currentPrice": 541.03,
      "marketValue": 1024.654742,
      "unrealizedPnl": 24.654742,
      "unrealizedPnlPct": 2.465,
      "change": 2.493
    },
    {
      "symbol": "TRIN",
      "qty": 173.73816156,
      "side": "long",
      "avgEntry": 14.389425,
      "currentPrice": 14.49,
      "marketValue": 2517.465961,
      "unrealizedPnl": 17.473716,
      "unrealizedPnlPct": 0.699,
      "change": -0.889
    },
    {
      "symbol": "TSM",
      "qty": 26.719543353,
      "side": "long",
      "avgEntry": 338.210072,
      "currentPrice": 342.26,
      "marketValue": 9145.030908,
      "unrealizedPnl": 108.212227,
      "unrealizedPnlPct": 1.197,
      "change": 1.126
    },
    {
      "symbol": "TSM260417C00350000",
      "qty": 2,
      "side": "long",
      "avgEntry": 12.4,
      "currentPrice": 12.2,
      "marketValue": 2440,
      "unrealizedPnl": -40,
      "unrealizedPnlPct": -1.6129999999999998,
      "change": 10.909
    },
    {
      "symbol": "TTAM",
      "qty": 15,
      "side": "long",
      "avgEntry": 14.89,
      "currentPrice": 14.7,
      "marketValue": 220.5,
      "unrealizedPnl": -2.85,
      "unrealizedPnlPct": -1.276,
      "change": 0
    },
    {
      "symbol": "UBER",
      "qty": 19.883351007,
      "side": "long",
      "avgEntry": 75.44,
      "currentPrice": 73.04,
      "marketValue": 1452.279958,
      "unrealizedPnl": -47.720042,
      "unrealizedPnlPct": -3.1809999999999996,
      "change": -2.769
    },
    {
      "symbol": "UNH",
      "qty": 6.723393564,
      "side": "long",
      "avgEntry": 270.779924,
      "currentPrice": 271.905,
      "marketValue": 1828.124327,
      "unrealizedPnl": 7.564329,
      "unrealizedPnlPct": 0.415,
      "change": 0.877
    },
    {
      "symbol": "UTHR",
      "qty": 0.401323706,
      "side": "long",
      "avgEntry": 532.196486,
      "currentPrice": 531.565,
      "marketValue": 213.329636,
      "unrealizedPnl": -0.25343,
      "unrealizedPnlPct": -0.11900000000000001,
      "change": 1.9849999999999999
    },
    {
      "symbol": "UUU",
      "qty": 575,
      "side": "long",
      "avgEntry": 6.126087,
      "currentPrice": 5.9516,
      "marketValue": 3422.17,
      "unrealizedPnl": -100.330025,
      "unrealizedPnlPct": -2.848,
      "change": 3.8670000000000004
    },
    {
      "symbol": "WFC",
      "qty": 61.959043571,
      "side": "long",
      "avgEntry": 77.029756,
      "currentPrice": 79.84,
      "marketValue": 4946.810039,
      "unrealizedPnl": 174.120031,
      "unrealizedPnlPct": 3.6479999999999997,
      "change": 1.9929999999999999
    },
    {
      "symbol": "WULF",
      "qty": 0.310526313,
      "side": "long",
      "avgEntry": 15.191392,
      "currentPrice": 16.085,
      "marketValue": 4.994816,
      "unrealizedPnl": 0.277489,
      "unrealizedPnlPct": 5.882,
      "change": -0.649
    },
    {
      "symbol": "XTWO",
      "qty": 101.308912129,
      "side": "long",
      "avgEntry": 49.354,
      "currentPrice": 49.17,
      "marketValue": 4981.359209,
      "unrealizedPnl": -18.64084,
      "unrealizedPnlPct": -0.373,
      "change": -0.062
    }
  ],
  "orders": [
    {
      "id": "a3329f7d-d15b-4b63-905f-9c088a8f778a",
      "symbol": "PICS",
      "side": "buy",
      "qty": 200,
      "type": "market",
      "status": "filled",
      "filledQty": 200,
      "filledAvgPrice": 11.47,
      "submittedAt": "2026-03-24T16:20:45.182264732Z",
      "filledAt": "2026-03-24T16:20:45.562901345Z"
    },
    {
      "id": "5878bdf9-2a38-4f88-9dc2-cd522a584ab6",
      "symbol": "AHCO",
      "side": "buy",
      "qty": 2000,
      "type": "market",
      "status": "filled",
      "filledQty": 180.831826401,
      "filledAvgPrice": 11.06,
      "submittedAt": "2026-03-24T16:11:56.640172Z",
      "filledAt": "2026-03-24T16:11:58.602857Z"
    },
    {
      "id": "c7074f24-c48a-496f-b61b-b2d8031815b3",
      "symbol": "KLTR",
      "side": "buy",
      "qty": 2000,
      "type": "market",
      "status": "filled",
      "filledQty": 1626.016260162,
      "filledAvgPrice": 1.23,
      "submittedAt": "2026-03-24T16:11:49.764705Z",
      "filledAt": "2026-03-24T16:11:50.781463Z"
    },
    {
      "id": "552d92f8-ff17-47c8-bba2-eb2c0694e5a6",
      "symbol": "TSM",
      "side": "buy",
      "qty": 3000,
      "type": "market",
      "status": "filled",
      "filledQty": 8.744061325,
      "filledAvgPrice": 343.09,
      "submittedAt": "2026-03-24T16:11:43.779548Z",
      "filledAt": "2026-03-24T16:11:44.319942Z"
    },
    {
      "id": "6d84fcb4-887d-45ea-9730-cec915bb5684",
      "symbol": "CHPT",
      "side": "sell",
      "qty": 300,
      "type": "market",
      "status": "filled",
      "filledQty": 300,
      "filledAvgPrice": 5.35,
      "submittedAt": "2026-03-24T15:41:00.876197Z",
      "filledAt": "2026-03-24T15:41:03.474821Z"
    },
    {
      "id": "489d0673-b398-4c90-848a-8c05daf34309",
      "symbol": "BETR",
      "side": "sell",
      "qty": 117.454232957,
      "type": "market",
      "status": "filled",
      "filledQty": 117.454232957,
      "filledAvgPrice": 28.75,
      "submittedAt": "2026-03-24T15:40:56.91755Z",
      "filledAt": "2026-03-24T15:40:57.635538Z"
    },
    {
      "id": "a0eb1bc4-5a3e-4948-b70c-352bf0ec9573",
      "symbol": "PICS",
      "side": "buy",
      "qty": 200,
      "type": "market",
      "status": "filled",
      "filledQty": 200,
      "filledAvgPrice": 11.56,
      "submittedAt": "2026-03-24T15:30:59.868878Z",
      "filledAt": "2026-03-24T15:31:01.822441Z"
    },
    {
      "id": "4db5f3df-76ee-4b88-8d23-ccf7de630715",
      "symbol": "UUU",
      "side": "buy",
      "qty": 200,
      "type": "market",
      "status": "filled",
      "filledQty": 200,
      "filledAvgPrice": 6.05,
      "submittedAt": "2026-03-24T15:21:36.175845Z",
      "filledAt": "2026-03-24T15:21:38.757071Z"
    },
    {
      "id": "4be7c848-45f0-49a7-ae36-dec89e3a9f87",
      "symbol": "OSUR",
      "side": "sell",
      "qty": 1314,
      "type": "market",
      "status": "filled",
      "filledQty": 1314,
      "filledAvgPrice": 3.04,
      "submittedAt": "2026-03-24T15:21:12.067841Z",
      "filledAt": "2026-03-24T15:21:12.67053Z"
    },
    {
      "id": "7a90d447-4140-4892-b3a9-0dd875f3e2d2",
      "symbol": "OSUR",
      "side": "buy",
      "qty": 3000,
      "type": "market",
      "status": "filled",
      "filledQty": 986.842105263,
      "filledAvgPrice": 3.04,
      "submittedAt": "2026-03-24T15:10:48.17001Z",
      "filledAt": "2026-03-24T15:10:48.99687Z"
    },
    {
      "id": "886c6617-5e6b-4648-9b80-ed517c97ff23",
      "symbol": "CRM",
      "side": "sell",
      "qty": 27.721065875,
      "type": "market",
      "status": "filled",
      "filledQty": 27.721065875,
      "filledAvgPrice": 184.22,
      "submittedAt": "2026-03-24T15:10:41.507477Z",
      "filledAt": "2026-03-24T15:10:42.836397Z"
    },
    {
      "id": "49c13bf4-923d-4234-8eae-33bf92400eef",
      "symbol": "UNH",
      "side": "buy",
      "qty": 1500,
      "type": "market",
      "status": "filled",
      "filledQty": 5.539143279,
      "filledAvgPrice": 270.8,
      "submittedAt": "2026-03-24T14:41:35.67915Z",
      "filledAt": "2026-03-24T14:41:37.309753Z"
    },
    {
      "id": "2c88908d-b06b-4ed8-80de-f6870a439920",
      "symbol": "OSUR",
      "side": "buy",
      "qty": 2000,
      "type": "market",
      "status": "filled",
      "filledQty": 662.251655629,
      "filledAvgPrice": 3.02,
      "submittedAt": "2026-03-24T14:41:31.1983Z",
      "filledAt": "2026-03-24T14:41:35.132139Z"
    },
    {
      "id": "db71e004-26a0-469c-91bc-a281777ef9ab",
      "symbol": "TSM260417C00350000",
      "side": "sell",
      "qty": 1,
      "type": "market",
      "status": "filled",
      "filledQty": 1,
      "filledAvgPrice": 10.15,
      "submittedAt": "2026-03-24T14:41:25.270608Z",
      "filledAt": "2026-03-24T14:41:25.36117Z"
    },
    {
      "id": "bc010a4c-7575-4e3a-9c2b-66c30d0776b7",
      "symbol": "UUU",
      "side": "buy",
      "qty": 125,
      "type": "market",
      "status": "filled",
      "filledQty": 125,
      "filledAvgPrice": 6.1,
      "submittedAt": "2026-03-24T14:31:12.585123Z",
      "filledAt": "2026-03-24T14:31:13.099756Z"
    },
    {
      "id": "ee525d21-c1bc-4079-98e0-211681909f0e",
      "symbol": "OSUR",
      "side": "buy",
      "qty": 500,
      "type": "market",
      "status": "filled",
      "filledQty": 500,
      "filledAvgPrice": 3,
      "submittedAt": "2026-03-24T14:31:08.847624Z",
      "filledAt": "2026-03-24T14:31:09.774155Z"
    },
    {
      "id": "c06d3cef-fa92-463d-9305-ae3dd011196e",
      "symbol": "TSM260417C00350000",
      "side": "sell",
      "qty": 2,
      "type": "market",
      "status": "filled",
      "filledQty": 2,
      "filledAvgPrice": 10.55,
      "submittedAt": "2026-03-24T14:31:00.64349Z",
      "filledAt": "2026-03-24T14:31:00.653742Z"
    },
    {
      "id": "667f7e72-93b8-42a0-93d8-b9592f1a8b56",
      "symbol": "AMR",
      "side": "sell",
      "qty": 11.745,
      "type": "market",
      "status": "filled",
      "filledQty": 11.745,
      "filledAvgPrice": 216,
      "submittedAt": "2026-03-24T14:30:55.965291Z",
      "filledAt": "2026-03-24T14:30:56.648459Z"
    },
    {
      "id": "4dee937f-2a3b-46a7-bfeb-6ca4b9fc6a0b",
      "symbol": "OSUR",
      "side": "buy",
      "qty": 200,
      "type": "market",
      "status": "filled",
      "filledQty": 200,
      "filledAvgPrice": 3.04,
      "submittedAt": "2026-03-24T14:21:07.873995Z",
      "filledAt": "2026-03-24T14:21:09.016294Z"
    },
    {
      "id": "bbccde20-4493-4055-a4f4-e30bc138be99",
      "symbol": "BETR",
      "side": "buy",
      "qty": 50,
      "type": "market",
      "status": "filled",
      "filledQty": 50,
      "filledAvgPrice": 29.54,
      "submittedAt": "2026-03-24T14:21:03.259552Z",
      "filledAt": "2026-03-24T14:21:04.551815Z"
    },
    {
      "id": "3c2b4fda-6562-4174-b33f-140de8eb4fc0",
      "symbol": "BCIC",
      "side": "buy",
      "qty": 1500,
      "type": "market",
      "status": "filled",
      "filledQty": 204.638472032,
      "filledAvgPrice": 7.33,
      "submittedAt": "2026-03-24T14:11:36.654598Z",
      "filledAt": "2026-03-24T14:11:37.467271Z"
    },
    {
      "id": "47f8cc68-1a31-4463-b8d8-d829373687b4",
      "symbol": "TSM260417C00350000",
      "side": "buy",
      "qty": 5,
      "type": "market",
      "status": "filled",
      "filledQty": 5,
      "filledAvgPrice": 12.4,
      "submittedAt": "2026-03-24T14:11:26.938403Z",
      "filledAt": "2026-03-24T14:11:26.97546Z"
    },
    {
      "id": "adcaa1ef-583f-4a81-8405-70fc41258c47",
      "symbol": "UBER260327C00076000",
      "side": "sell",
      "qty": 5,
      "type": "market",
      "status": "filled",
      "filledQty": 5,
      "filledAvgPrice": 0.3,
      "submittedAt": "2026-03-24T14:11:17.915248Z",
      "filledAt": "2026-03-24T14:11:17.965221Z"
    },
    {
      "id": "46002312-9822-4a1e-acfc-d451c2c0bc2f",
      "symbol": "BETR260417C00030000",
      "side": "sell",
      "qty": 5,
      "type": "market",
      "status": "filled",
      "filledQty": 5,
      "filledAvgPrice": 1.5,
      "submittedAt": "2026-03-24T14:11:08.611414Z",
      "filledAt": "2026-03-24T14:11:08.704556Z"
    },
    {
      "id": "efc9d640-ed2e-464d-819e-4f56bab4587d",
      "symbol": "CHPT",
      "side": "buy",
      "qty": 300,
      "type": "market",
      "status": "filled",
      "filledQty": 300,
      "filledAvgPrice": 5.41,
      "submittedAt": "2026-03-24T13:52:17.636376Z",
      "filledAt": "2026-03-24T13:52:18.350221Z"
    },
    {
      "id": "15b2e647-8b35-49d6-84c0-52b9ab6dcec2",
      "symbol": "UBER260327C00076000",
      "side": "sell",
      "qty": 5,
      "type": "market",
      "status": "filled",
      "filledQty": 5,
      "filledAvgPrice": 0.38,
      "submittedAt": "2026-03-24T13:51:40.420893Z",
      "filledAt": "2026-03-24T13:51:40.534797Z"
    },
    {
      "id": "cf9f7b92-0387-43c2-aa7a-bcca8866d873",
      "symbol": "PHR",
      "side": "sell",
      "qty": 355,
      "type": "market",
      "status": "filled",
      "filledQty": 355,
      "filledAvgPrice": 11.21,
      "submittedAt": "2026-03-24T13:51:36.173482Z",
      "filledAt": "2026-03-24T13:51:36.447397Z"
    },
    {
      "id": "47d73f54-fab2-4627-a14b-44a6c5b248aa",
      "symbol": "BETR260417C00030000",
      "side": "buy",
      "qty": 5,
      "type": "market",
      "status": "filled",
      "filledQty": 5,
      "filledAvgPrice": 4.7,
      "submittedAt": "2026-03-24T13:41:19.050168Z",
      "filledAt": "2026-03-24T13:41:19.058392Z"
    },
    {
      "id": "440bb39b-79be-40c2-b7c6-773e5d359e45",
      "symbol": "UUU",
      "side": "buy",
      "qty": 250,
      "type": "market",
      "status": "filled",
      "filledQty": 250,
      "filledAvgPrice": 6.2,
      "submittedAt": "2026-03-24T13:41:14.087397Z",
      "filledAt": "2026-03-24T13:41:17.582717Z"
    },
    {
      "id": "5cc7a3a6-80c6-41ac-b3b9-08c1f452a180",
      "symbol": "BETR",
      "side": "buy",
      "qty": 2000,
      "type": "market",
      "status": "filled",
      "filledQty": 66.00660066,
      "filledAvgPrice": 30.3,
      "submittedAt": "2026-03-24T13:41:06.447953Z",
      "filledAt": "2026-03-24T13:41:07.30069Z"
    },
    {
      "id": "c49b61f9-e92b-4237-b903-ee0ed186346e",
      "symbol": "SBSW",
      "side": "sell",
      "qty": 100,
      "type": "market",
      "status": "filled",
      "filledQty": 100,
      "filledAvgPrice": 10.86,
      "submittedAt": "2026-03-24T13:41:01.031433Z",
      "filledAt": "2026-03-24T13:41:04.654222Z"
    },
    {
      "id": "1e3880ea-f85f-43d5-91dd-e1c49d34567e",
      "symbol": "PHR",
      "side": "sell",
      "qty": 100,
      "type": "market",
      "status": "filled",
      "filledQty": 100,
      "filledAvgPrice": 11.2,
      "submittedAt": "2026-03-24T13:40:56.953003Z",
      "filledAt": "2026-03-24T13:40:58.782244Z"
    },
    {
      "id": "894b1dca-39ac-4f7d-a4b9-b57785d2a50b",
      "symbol": "TSM",
      "side": "sell",
      "qty": 5,
      "type": "market",
      "status": "filled",
      "filledQty": 5,
      "filledAvgPrice": 338.37,
      "submittedAt": "2026-03-24T13:40:50.594591Z",
      "filledAt": "2026-03-24T13:40:51.866092Z"
    },
    {
      "id": "32889a16-cf68-497e-b795-056281fc389c",
      "symbol": "NVDA260410C00180000",
      "side": "buy",
      "qty": 3,
      "type": "market",
      "status": "filled",
      "filledQty": 3,
      "filledAvgPrice": 3.5,
      "submittedAt": "2026-03-24T13:31:32.474646Z",
      "filledAt": "2026-03-24T13:31:32.48675Z"
    },
    {
      "id": "4f002bd1-2ecc-434c-9944-f3ee70ea912e",
      "symbol": "OSUR",
      "side": "buy",
      "qty": 170,
      "type": "market",
      "status": "filled",
      "filledQty": 170,
      "filledAvgPrice": 3.187,
      "submittedAt": "2026-03-24T13:31:17.588906Z",
      "filledAt": "2026-03-24T13:34:21.159606Z"
    },
    {
      "id": "5db006cf-4b83-4253-b2d1-3db517eb396c",
      "symbol": "AHCO",
      "side": "buy",
      "qty": 50,
      "type": "market",
      "status": "filled",
      "filledQty": 50,
      "filledAvgPrice": 10.723199,
      "submittedAt": "2026-03-24T13:31:05.925034Z",
      "filledAt": "2026-03-24T13:34:27.638104Z"
    },
    {
      "id": "6399fd21-db57-42a9-8123-5fb007beeb5e",
      "symbol": "WULF260410C00015000",
      "side": "sell",
      "qty": 10,
      "type": "limit",
      "status": "filled",
      "filledQty": 10,
      "filledAvgPrice": 1.99,
      "submittedAt": "2026-03-24T13:30:03.889766Z",
      "filledAt": "2026-03-24T13:31:52.917471Z"
    },
    {
      "id": "f877514a-61ad-4b71-9419-14aa30d5eaac",
      "symbol": "NVDA260327C00190000",
      "side": "sell",
      "qty": 1,
      "type": "limit",
      "status": "new",
      "filledQty": 0,
      "filledAvgPrice": 0,
      "submittedAt": "2026-03-24T13:30:03.868454Z",
      "filledAt": null
    },
    {
      "id": "84e82dd4-74d9-48fa-92c6-dd3342c7b1e2",
      "symbol": "TSM",
      "side": "buy",
      "qty": 1000,
      "type": "market",
      "status": "filled",
      "filledQty": 2.975482028,
      "filledAvgPrice": 336.08,
      "submittedAt": "2026-03-24T13:11:40.792928Z",
      "filledAt": "2026-03-24T13:30:29.077959Z"
    },
    {
      "id": "4aaab841-d237-45c3-b8bf-1eb80301fc05",
      "symbol": "MKTW",
      "side": "buy",
      "qty": 68,
      "type": "market",
      "status": "filled",
      "filledQty": 68,
      "filledAvgPrice": 15.49,
      "submittedAt": "2026-03-24T13:11:26.853409Z",
      "filledAt": "2026-03-24T13:32:22.445378Z"
    },
    {
      "id": "bb896850-9b35-49af-8683-098b147c2f9f",
      "symbol": "OSUR",
      "side": "buy",
      "qty": 1500,
      "type": "market",
      "status": "filled",
      "filledQty": 467.576323988,
      "filledAvgPrice": 3.208031,
      "submittedAt": "2026-03-24T13:11:17.511286Z",
      "filledAt": "2026-03-24T13:34:34.383692Z"
    },
    {
      "id": "435786d0-f7fe-4440-8e56-02b8500638d8",
      "symbol": "AHCO",
      "side": "buy",
      "qty": 2000,
      "type": "market",
      "status": "filled",
      "filledQty": 188.501413761,
      "filledAvgPrice": 10.61,
      "submittedAt": "2026-03-24T13:11:12.242255Z",
      "filledAt": "2026-03-24T13:31:09.726581Z"
    },
    {
      "id": "46a9e3d0-cedf-4b28-ab41-e2e844648eef",
      "symbol": "FIVE",
      "side": "buy",
      "qty": 5,
      "type": "market",
      "status": "filled",
      "filledQty": 5,
      "filledAvgPrice": 229.36,
      "submittedAt": "2026-03-24T13:01:40.7333Z",
      "filledAt": "2026-03-24T13:32:44.611906Z"
    },
    {
      "id": "a44ef0c1-2937-4c43-a5d3-9279582d471d",
      "symbol": "SFM",
      "side": "buy",
      "qty": 15,
      "type": "market",
      "status": "filled",
      "filledQty": 15,
      "filledAvgPrice": 79.46,
      "submittedAt": "2026-03-24T13:01:36.747207Z",
      "filledAt": "2026-03-24T13:32:04.979177Z"
    },
    {
      "id": "b2ee1fce-c377-44e6-baef-2847d358c6fe",
      "symbol": "TSM",
      "side": "buy",
      "qty": 20,
      "type": "market",
      "status": "filled",
      "filledQty": 20,
      "filledAvgPrice": 335.8,
      "submittedAt": "2026-03-24T13:01:32.331877Z",
      "filledAt": "2026-03-24T13:30:12.665974Z"
    },
    {
      "id": "ff72bcb7-2d66-4acd-b67c-4c665bfef945",
      "symbol": "PHR",
      "side": "sell",
      "qty": 14.037495,
      "type": "market",
      "status": "filled",
      "filledQty": 14.037495,
      "filledAvgPrice": 11.84,
      "submittedAt": "2026-03-23T19:51:48.78039Z",
      "filledAt": "2026-03-23T19:51:50.449904Z"
    },
    {
      "id": "2a57b3f1-2966-42b7-94ac-f693ef4079c6",
      "symbol": "CRM",
      "side": "sell",
      "qty": 1.972991,
      "type": "market",
      "status": "filled",
      "filledQty": 1.972991,
      "filledAvgPrice": 195.09,
      "submittedAt": "2026-03-23T19:51:43.42157Z",
      "filledAt": "2026-03-23T19:51:44.230587Z"
    },
    {
      "id": "2a206f3b-58c8-4ab2-b158-0416e0e1549e",
      "symbol": "SBSW",
      "side": "sell",
      "qty": 144,
      "type": "market",
      "status": "filled",
      "filledQty": 144,
      "filledAvgPrice": 11.339861,
      "submittedAt": "2026-03-23T19:51:37.727368Z",
      "filledAt": "2026-03-23T19:51:40.864184Z"
    },
    {
      "id": "9645e6d5-db0d-4034-89d2-7568b36fc2f4",
      "symbol": "STIM",
      "side": "sell",
      "qty": 80,
      "type": "market",
      "status": "filled",
      "filledQty": 80,
      "filledAvgPrice": 1.6,
      "submittedAt": "2026-03-23T19:40:56.150901Z",
      "filledAt": "2026-03-23T19:40:56.354619Z"
    },
    {
      "id": "2951216c-e7a1-4017-aae9-8c7e0fc5f8b0",
      "symbol": "UTHR",
      "side": "sell",
      "qty": 9,
      "type": "market",
      "status": "filled",
      "filledQty": 9,
      "filledAvgPrice": 518.81,
      "submittedAt": "2026-03-23T19:40:52.581149Z",
      "filledAt": "2026-03-23T19:40:54.331397Z"
    }
  ],
  "history": [
    {
      "action": "BUY",
      "ticker": "PICS",
      "qty": 200,
      "price": 11.47,
      "date": "2026-03-24",
      "time": "2026-03-24T16:20:45.562901Z",
      "orderId": "a3329f7d-d15b-4b63-905f-9c088a8f778a"
    },
    {
      "action": "BUY",
      "ticker": "AHCO",
      "qty": 1.831826401,
      "price": 11.06,
      "date": "2026-03-24",
      "time": "2026-03-24T16:11:58.60533Z",
      "orderId": "5878bdf9-2a38-4f88-9dc2-cd522a584ab6"
    },
    {
      "action": "BUY",
      "ticker": "AHCO",
      "qty": 11,
      "price": 11.06,
      "date": "2026-03-24",
      "time": "2026-03-24T16:11:58.602857Z",
      "orderId": "5878bdf9-2a38-4f88-9dc2-cd522a584ab6"
    },
    {
      "action": "BUY",
      "ticker": "AHCO",
      "qty": 3,
      "price": 11.06,
      "date": "2026-03-24",
      "time": "2026-03-24T16:11:58.02894Z",
      "orderId": "5878bdf9-2a38-4f88-9dc2-cd522a584ab6"
    },
    {
      "action": "BUY",
      "ticker": "AHCO",
      "qty": 1,
      "price": 11.06,
      "date": "2026-03-24",
      "time": "2026-03-24T16:11:57.693267Z",
      "orderId": "5878bdf9-2a38-4f88-9dc2-cd522a584ab6"
    },
    {
      "action": "BUY",
      "ticker": "AHCO",
      "qty": 164,
      "price": 11.06,
      "date": "2026-03-24",
      "time": "2026-03-24T16:11:57.107333Z",
      "orderId": "5878bdf9-2a38-4f88-9dc2-cd522a584ab6"
    },
    {
      "action": "BUY",
      "ticker": "KLTR",
      "qty": 1.016260162,
      "price": 1.23,
      "date": "2026-03-24",
      "time": "2026-03-24T16:11:50.78354Z",
      "orderId": "c7074f24-c48a-496f-b61b-b2d8031815b3"
    },
    {
      "action": "BUY",
      "ticker": "KLTR",
      "qty": 1386,
      "price": 1.23,
      "date": "2026-03-24",
      "time": "2026-03-24T16:11:50.781463Z",
      "orderId": "c7074f24-c48a-496f-b61b-b2d8031815b3"
    },
    {
      "action": "BUY",
      "ticker": "KLTR",
      "qty": 239,
      "price": 1.23,
      "date": "2026-03-24",
      "time": "2026-03-24T16:11:50.440902Z",
      "orderId": "c7074f24-c48a-496f-b61b-b2d8031815b3"
    },
    {
      "action": "BUY",
      "ticker": "TSM",
      "qty": 1.744061325,
      "price": 343.09,
      "date": "2026-03-24",
      "time": "2026-03-24T16:11:44.322544Z",
      "orderId": "552d92f8-ff17-47c8-bba2-eb2c0694e5a6"
    },
    {
      "action": "BUY",
      "ticker": "TSM",
      "qty": 7,
      "price": 343.09,
      "date": "2026-03-24",
      "time": "2026-03-24T16:11:44.319942Z",
      "orderId": "552d92f8-ff17-47c8-bba2-eb2c0694e5a6"
    },
    {
      "action": "SELL",
      "ticker": "CHPT",
      "qty": 122,
      "price": 5.35,
      "date": "2026-03-24",
      "time": "2026-03-24T15:41:03.474821Z",
      "orderId": "6d84fcb4-887d-45ea-9730-cec915bb5684"
    },
    {
      "action": "SELL",
      "ticker": "CHPT",
      "qty": 115,
      "price": 5.35,
      "date": "2026-03-24",
      "time": "2026-03-24T15:41:02.72042Z",
      "orderId": "6d84fcb4-887d-45ea-9730-cec915bb5684"
    },
    {
      "action": "SELL",
      "ticker": "CHPT",
      "qty": 63,
      "price": 5.35,
      "date": "2026-03-24",
      "time": "2026-03-24T15:41:02.215935Z",
      "orderId": "6d84fcb4-887d-45ea-9730-cec915bb5684"
    },
    {
      "action": "SELL",
      "ticker": "BETR",
      "qty": 0.454232957,
      "price": 28.75,
      "date": "2026-03-24",
      "time": "2026-03-24T15:40:57.637981Z",
      "orderId": "489d0673-b398-4c90-848a-8c05daf34309"
    },
    {
      "action": "SELL",
      "ticker": "BETR",
      "qty": 117,
      "price": 28.75,
      "date": "2026-03-24",
      "time": "2026-03-24T15:40:57.635538Z",
      "orderId": "489d0673-b398-4c90-848a-8c05daf34309"
    },
    {
      "action": "BUY",
      "ticker": "PICS",
      "qty": 1,
      "price": 11.56,
      "date": "2026-03-24",
      "time": "2026-03-24T15:31:01.822441Z",
      "orderId": "a0eb1bc4-5a3e-4948-b70c-352bf0ec9573"
    },
    {
      "action": "BUY",
      "ticker": "PICS",
      "qty": 6,
      "price": 11.56,
      "date": "2026-03-24",
      "time": "2026-03-24T15:31:01.422733Z",
      "orderId": "a0eb1bc4-5a3e-4948-b70c-352bf0ec9573"
    },
    {
      "action": "BUY",
      "ticker": "PICS",
      "qty": 193,
      "price": 11.56,
      "date": "2026-03-24",
      "time": "2026-03-24T15:31:00.70336Z",
      "orderId": "a0eb1bc4-5a3e-4948-b70c-352bf0ec9573"
    },
    {
      "action": "BUY",
      "ticker": "UUU",
      "qty": 1,
      "price": 6.05,
      "date": "2026-03-24",
      "time": "2026-03-24T15:21:38.757071Z",
      "orderId": "4db5f3df-76ee-4b88-8d23-ccf7de630715"
    },
    {
      "action": "BUY",
      "ticker": "UUU",
      "qty": 1,
      "price": 6.05,
      "date": "2026-03-24",
      "time": "2026-03-24T15:21:38.219884Z",
      "orderId": "4db5f3df-76ee-4b88-8d23-ccf7de630715"
    },
    {
      "action": "BUY",
      "ticker": "UUU",
      "qty": 1,
      "price": 6.05,
      "date": "2026-03-24",
      "time": "2026-03-24T15:21:38.056022Z",
      "orderId": "4db5f3df-76ee-4b88-8d23-ccf7de630715"
    },
    {
      "action": "BUY",
      "ticker": "UUU",
      "qty": 9,
      "price": 6.05,
      "date": "2026-03-24",
      "time": "2026-03-24T15:21:37.233266Z",
      "orderId": "4db5f3df-76ee-4b88-8d23-ccf7de630715"
    },
    {
      "action": "BUY",
      "ticker": "UUU",
      "qty": 188,
      "price": 6.05,
      "date": "2026-03-24",
      "time": "2026-03-24T15:21:36.887079Z",
      "orderId": "4db5f3df-76ee-4b88-8d23-ccf7de630715"
    },
    {
      "action": "SELL",
      "ticker": "OSUR",
      "qty": 1314,
      "price": 3.04,
      "date": "2026-03-24",
      "time": "2026-03-24T15:21:12.67053Z",
      "orderId": "4be7c848-45f0-49a7-ae36-dec89e3a9f87"
    },
    {
      "action": "BUY",
      "ticker": "OSUR",
      "qty": 1.842105263,
      "price": 3.04,
      "date": "2026-03-24",
      "time": "2026-03-24T15:10:49.004171Z",
      "orderId": "7a90d447-4140-4892-b3a9-0dd875f3e2d2"
    },
    {
      "action": "BUY",
      "ticker": "OSUR",
      "qty": 985,
      "price": 3.04,
      "date": "2026-03-24",
      "time": "2026-03-24T15:10:48.99687Z",
      "orderId": "7a90d447-4140-4892-b3a9-0dd875f3e2d2"
    },
    {
      "action": "SELL",
      "ticker": "CRM",
      "qty": 0.721065875,
      "price": 184.22,
      "date": "2026-03-24",
      "time": "2026-03-24T15:10:42.838555Z",
      "orderId": "886c6617-5e6b-4648-9b80-ed517c97ff23"
    },
    {
      "action": "SELL",
      "ticker": "CRM",
      "qty": 20,
      "price": 184.22,
      "date": "2026-03-24",
      "time": "2026-03-24T15:10:42.836397Z",
      "orderId": "886c6617-5e6b-4648-9b80-ed517c97ff23"
    },
    {
      "action": "SELL",
      "ticker": "CRM",
      "qty": 7,
      "price": 184.22,
      "date": "2026-03-24",
      "time": "2026-03-24T15:10:42.229426Z",
      "orderId": "886c6617-5e6b-4648-9b80-ed517c97ff23"
    },
    {
      "action": "BUY",
      "ticker": "UNH",
      "qty": 1.539143279,
      "price": 270.8,
      "date": "2026-03-24",
      "time": "2026-03-24T14:41:37.313362Z",
      "orderId": "49c13bf4-923d-4234-8eae-33bf92400eef"
    },
    {
      "action": "BUY",
      "ticker": "UNH",
      "qty": 1,
      "price": 270.8,
      "date": "2026-03-24",
      "time": "2026-03-24T14:41:37.309753Z",
      "orderId": "49c13bf4-923d-4234-8eae-33bf92400eef"
    },
    {
      "action": "BUY",
      "ticker": "UNH",
      "qty": 2,
      "price": 270.8,
      "date": "2026-03-24",
      "time": "2026-03-24T14:41:36.600761Z",
      "orderId": "49c13bf4-923d-4234-8eae-33bf92400eef"
    },
    {
      "action": "BUY",
      "ticker": "UNH",
      "qty": 1,
      "price": 270.8,
      "date": "2026-03-24",
      "time": "2026-03-24T14:41:35.984303Z",
      "orderId": "49c13bf4-923d-4234-8eae-33bf92400eef"
    },
    {
      "action": "BUY",
      "ticker": "OSUR",
      "qty": 1.251655629,
      "price": 3.02,
      "date": "2026-03-24",
      "time": "2026-03-24T14:41:35.135245Z",
      "orderId": "2c88908d-b06b-4ed8-80de-f6870a439920"
    },
    {
      "action": "BUY",
      "ticker": "OSUR",
      "qty": 1,
      "price": 3.02,
      "date": "2026-03-24",
      "time": "2026-03-24T14:41:35.132139Z",
      "orderId": "2c88908d-b06b-4ed8-80de-f6870a439920"
    },
    {
      "action": "BUY",
      "ticker": "OSUR",
      "qty": 3,
      "price": 3.02,
      "date": "2026-03-24",
      "time": "2026-03-24T14:41:34.934645Z",
      "orderId": "2c88908d-b06b-4ed8-80de-f6870a439920"
    },
    {
      "action": "BUY",
      "ticker": "OSUR",
      "qty": 10,
      "price": 3.02,
      "date": "2026-03-24",
      "time": "2026-03-24T14:41:34.329806Z",
      "orderId": "2c88908d-b06b-4ed8-80de-f6870a439920"
    },
    {
      "action": "BUY",
      "ticker": "OSUR",
      "qty": 59,
      "price": 3.02,
      "date": "2026-03-24",
      "time": "2026-03-24T14:41:33.539968Z",
      "orderId": "2c88908d-b06b-4ed8-80de-f6870a439920"
    },
    {
      "action": "BUY",
      "ticker": "OSUR",
      "qty": 214,
      "price": 3.02,
      "date": "2026-03-24",
      "time": "2026-03-24T14:41:33.277099Z",
      "orderId": "2c88908d-b06b-4ed8-80de-f6870a439920"
    },
    {
      "action": "BUY",
      "ticker": "OSUR",
      "qty": 201,
      "price": 3.02,
      "date": "2026-03-24",
      "time": "2026-03-24T14:41:32.811954Z",
      "orderId": "2c88908d-b06b-4ed8-80de-f6870a439920"
    },
    {
      "action": "BUY",
      "ticker": "OSUR",
      "qty": 173,
      "price": 3.02,
      "date": "2026-03-24",
      "time": "2026-03-24T14:41:31.937444Z",
      "orderId": "2c88908d-b06b-4ed8-80de-f6870a439920"
    },
    {
      "action": "SELL",
      "ticker": "TSM260417C00350000",
      "qty": 1,
      "price": 10.15,
      "date": "2026-03-24",
      "time": "2026-03-24T14:41:25.36117Z",
      "orderId": "db71e004-26a0-469c-91bc-a281777ef9ab"
    },
    {
      "action": "BUY",
      "ticker": "UUU",
      "qty": 125,
      "price": 6.1,
      "date": "2026-03-24",
      "time": "2026-03-24T14:31:13.099756Z",
      "orderId": "bc010a4c-7575-4e3a-9c2b-66c30d0776b7"
    },
    {
      "action": "BUY",
      "ticker": "OSUR",
      "qty": 500,
      "price": 3,
      "date": "2026-03-24",
      "time": "2026-03-24T14:31:09.774155Z",
      "orderId": "ee525d21-c1bc-4079-98e0-211681909f0e"
    },
    {
      "action": "SELL",
      "ticker": "TSM260417C00350000",
      "qty": 2,
      "price": 10.55,
      "date": "2026-03-24",
      "time": "2026-03-24T14:31:00.653742Z",
      "orderId": "c06d3cef-fa92-463d-9305-ae3dd011196e"
    },
    {
      "action": "SELL",
      "ticker": "AMR",
      "qty": 0.745,
      "price": 216,
      "date": "2026-03-24",
      "time": "2026-03-24T14:30:56.650697Z",
      "orderId": "667f7e72-93b8-42a0-93d8-b9592f1a8b56"
    },
    {
      "action": "SELL",
      "ticker": "AMR",
      "qty": 11,
      "price": 216,
      "date": "2026-03-24",
      "time": "2026-03-24T14:30:56.648459Z",
      "orderId": "667f7e72-93b8-42a0-93d8-b9592f1a8b56"
    },
    {
      "action": "BUY",
      "ticker": "OSUR",
      "qty": 200,
      "price": 3.04,
      "date": "2026-03-24",
      "time": "2026-03-24T14:21:09.016294Z",
      "orderId": "4dee937f-2a3b-46a7-bfeb-6ca4b9fc6a0b"
    },
    {
      "action": "BUY",
      "ticker": "BETR",
      "qty": 18,
      "price": 29.54,
      "date": "2026-03-24",
      "time": "2026-03-24T14:21:04.551815Z",
      "orderId": "bbccde20-4493-4055-a4f4-e30bc138be99"
    },
    {
      "action": "BUY",
      "ticker": "BETR",
      "qty": 32,
      "price": 29.54,
      "date": "2026-03-24",
      "time": "2026-03-24T14:21:03.65783Z",
      "orderId": "bbccde20-4493-4055-a4f4-e30bc138be99"
    },
    {
      "action": "BUY",
      "ticker": "BCIC",
      "qty": 1.638472032,
      "price": 7.33,
      "date": "2026-03-24",
      "time": "2026-03-24T14:11:37.469322Z",
      "orderId": "3c2b4fda-6562-4174-b33f-140de8eb4fc0"
    },
    {
      "action": "BUY",
      "ticker": "BCIC",
      "qty": 60,
      "price": 7.33,
      "date": "2026-03-24",
      "time": "2026-03-24T14:11:37.467271Z",
      "orderId": "3c2b4fda-6562-4174-b33f-140de8eb4fc0"
    },
    {
      "action": "BUY",
      "ticker": "BCIC",
      "qty": 143,
      "price": 7.33,
      "date": "2026-03-24",
      "time": "2026-03-24T14:11:37.275137Z",
      "orderId": "3c2b4fda-6562-4174-b33f-140de8eb4fc0"
    },
    {
      "action": "BUY",
      "ticker": "TSM260417C00350000",
      "qty": 5,
      "price": 12.4,
      "date": "2026-03-24",
      "time": "2026-03-24T14:11:26.97546Z",
      "orderId": "47f8cc68-1a31-4463-b8d8-d829373687b4"
    },
    {
      "action": "SELL",
      "ticker": "UBER260327C00076000",
      "qty": 5,
      "price": 0.3,
      "date": "2026-03-24",
      "time": "2026-03-24T14:11:17.965221Z",
      "orderId": "adcaa1ef-583f-4a81-8405-70fc41258c47"
    },
    {
      "action": "SELL",
      "ticker": "BETR260417C00030000",
      "qty": 5,
      "price": 1.5,
      "date": "2026-03-24",
      "time": "2026-03-24T14:11:08.704556Z",
      "orderId": "46002312-9822-4a1e-acfc-d451c2c0bc2f"
    },
    {
      "action": "BUY",
      "ticker": "CHPT",
      "qty": 231,
      "price": 5.41,
      "date": "2026-03-24",
      "time": "2026-03-24T13:52:18.350221Z",
      "orderId": "efc9d640-ed2e-464d-819e-4f56bab4587d"
    },
    {
      "action": "BUY",
      "ticker": "CHPT",
      "qty": 69,
      "price": 5.41,
      "date": "2026-03-24",
      "time": "2026-03-24T13:52:18.161599Z",
      "orderId": "efc9d640-ed2e-464d-819e-4f56bab4587d"
    },
    {
      "action": "SELL",
      "ticker": "UBER260327C00076000",
      "qty": 5,
      "price": 0.38,
      "date": "2026-03-24",
      "time": "2026-03-24T13:51:40.534797Z",
      "orderId": "15b2e647-8b35-49d6-84c0-52b9ab6dcec2"
    },
    {
      "action": "SELL",
      "ticker": "PHR",
      "qty": 355,
      "price": 11.21,
      "date": "2026-03-24",
      "time": "2026-03-24T13:51:36.447397Z",
      "orderId": "cf9f7b92-0387-43c2-aa7a-bcca8866d873"
    },
    {
      "action": "BUY",
      "ticker": "BETR260417C00030000",
      "qty": 5,
      "price": 4.7,
      "date": "2026-03-24",
      "time": "2026-03-24T13:41:19.058392Z",
      "orderId": "47d73f54-fab2-4627-a14b-44a6c5b248aa"
    },
    {
      "action": "BUY",
      "ticker": "UUU",
      "qty": 1,
      "price": 6.2,
      "date": "2026-03-24",
      "time": "2026-03-24T13:41:17.582717Z",
      "orderId": "440bb39b-79be-40c2-b7c6-773e5d359e45"
    },
    {
      "action": "BUY",
      "ticker": "UUU",
      "qty": 1,
      "price": 6.2,
      "date": "2026-03-24",
      "time": "2026-03-24T13:41:16.660882Z",
      "orderId": "440bb39b-79be-40c2-b7c6-773e5d359e45"
    },
    {
      "action": "BUY",
      "ticker": "UUU",
      "qty": 41,
      "price": 6.2,
      "date": "2026-03-24",
      "time": "2026-03-24T13:41:16.405823Z",
      "orderId": "440bb39b-79be-40c2-b7c6-773e5d359e45"
    },
    {
      "action": "BUY",
      "ticker": "UUU",
      "qty": 115,
      "price": 6.2,
      "date": "2026-03-24",
      "time": "2026-03-24T13:41:15.54993Z",
      "orderId": "440bb39b-79be-40c2-b7c6-773e5d359e45"
    },
    {
      "action": "BUY",
      "ticker": "UUU",
      "qty": 92,
      "price": 6.2,
      "date": "2026-03-24",
      "time": "2026-03-24T13:41:14.889269Z",
      "orderId": "440bb39b-79be-40c2-b7c6-773e5d359e45"
    },
    {
      "action": "BUY",
      "ticker": "BETR",
      "qty": 1.00660066,
      "price": 30.3,
      "date": "2026-03-24",
      "time": "2026-03-24T13:41:07.303031Z",
      "orderId": "5cc7a3a6-80c6-41ac-b3b9-08c1f452a180"
    },
    {
      "action": "BUY",
      "ticker": "BETR",
      "qty": 65,
      "price": 30.3,
      "date": "2026-03-24",
      "time": "2026-03-24T13:41:07.30069Z",
      "orderId": "5cc7a3a6-80c6-41ac-b3b9-08c1f452a180"
    },
    {
      "action": "SELL",
      "ticker": "SBSW",
      "qty": 7,
      "price": 10.86,
      "date": "2026-03-24",
      "time": "2026-03-24T13:41:04.654222Z",
      "orderId": "c49b61f9-e92b-4237-b903-ee0ed186346e"
    },
    {
      "action": "SELL",
      "ticker": "SBSW",
      "qty": 4,
      "price": 10.86,
      "date": "2026-03-24",
      "time": "2026-03-24T13:41:04.247438Z",
      "orderId": "c49b61f9-e92b-4237-b903-ee0ed186346e"
    },
    {
      "action": "SELL",
      "ticker": "SBSW",
      "qty": 57,
      "price": 10.86,
      "date": "2026-03-24",
      "time": "2026-03-24T13:41:03.334755Z",
      "orderId": "c49b61f9-e92b-4237-b903-ee0ed186346e"
    },
    {
      "action": "SELL",
      "ticker": "SBSW",
      "qty": 32,
      "price": 10.86,
      "date": "2026-03-24",
      "time": "2026-03-24T13:41:02.352771Z",
      "orderId": "c49b61f9-e92b-4237-b903-ee0ed186346e"
    },
    {
      "action": "SELL",
      "ticker": "PHR",
      "qty": 73,
      "price": 11.2,
      "date": "2026-03-24",
      "time": "2026-03-24T13:40:58.782244Z",
      "orderId": "1e3880ea-f85f-43d5-91dd-e1c49d34567e"
    },
    {
      "action": "SELL",
      "ticker": "PHR",
      "qty": 27,
      "price": 11.2,
      "date": "2026-03-24",
      "time": "2026-03-24T13:40:57.75399Z",
      "orderId": "1e3880ea-f85f-43d5-91dd-e1c49d34567e"
    },
    {
      "action": "SELL",
      "ticker": "TSM",
      "qty": 2,
      "price": 338.37,
      "date": "2026-03-24",
      "time": "2026-03-24T13:40:51.866092Z",
      "orderId": "894b1dca-39ac-4f7d-a4b9-b57785d2a50b"
    },
    {
      "action": "SELL",
      "ticker": "TSM",
      "qty": 3,
      "price": 338.37,
      "date": "2026-03-24",
      "time": "2026-03-24T13:40:51.165209Z",
      "orderId": "894b1dca-39ac-4f7d-a4b9-b57785d2a50b"
    },
    {
      "action": "BUY",
      "ticker": "OSUR",
      "qty": -14.423676012,
      "price": 3.21,
      "date": "2026-03-24",
      "time": "2026-03-24T13:34:34.386774Z",
      "orderId": "bb896850-9b35-49af-8683-098b147c2f9f"
    },
    {
      "action": "BUY",
      "ticker": "OSUR",
      "qty": 1,
      "price": 3.21,
      "date": "2026-03-24",
      "time": "2026-03-24T13:34:34.383692Z",
      "orderId": "bb896850-9b35-49af-8683-098b147c2f9f"
    },
    {
      "action": "BUY",
      "ticker": "AHCO",
      "qty": 1,
      "price": 10.8,
      "date": "2026-03-24",
      "time": "2026-03-24T13:34:27.638104Z",
      "orderId": "5db006cf-4b83-4253-b2d1-3db517eb396c"
    },
    {
      "action": "BUY",
      "ticker": "OSUR",
      "qty": 11,
      "price": 3.21,
      "date": "2026-03-24",
      "time": "2026-03-24T13:34:21.159606Z",
      "orderId": "4f002bd1-2ecc-434c-9944-f3ee70ea912e"
    },
    {
      "action": "BUY",
      "ticker": "AHCO",
      "qty": 2,
      "price": 10.8,
      "date": "2026-03-24",
      "time": "2026-03-24T13:34:20.890384Z",
      "orderId": "5db006cf-4b83-4253-b2d1-3db517eb396c"
    },
    {
      "action": "BUY",
      "ticker": "OSUR",
      "qty": 3,
      "price": 3.19,
      "date": "2026-03-24",
      "time": "2026-03-24T13:34:17.76269Z",
      "orderId": "bb896850-9b35-49af-8683-098b147c2f9f"
    },
    {
      "action": "BUY",
      "ticker": "OSUR",
      "qty": 29,
      "price": 3.2,
      "date": "2026-03-24",
      "time": "2026-03-24T13:34:08.523132Z",
      "orderId": "4f002bd1-2ecc-434c-9944-f3ee70ea912e"
    },
    {
      "action": "BUY",
      "ticker": "AHCO",
      "qty": 5,
      "price": 10.8,
      "date": "2026-03-24",
      "time": "2026-03-24T13:34:07.672297Z",
      "orderId": "5db006cf-4b83-4253-b2d1-3db517eb396c"
    },
    {
      "action": "BUY",
      "ticker": "OSUR",
      "qty": 24,
      "price": 3.2,
      "date": "2026-03-24",
      "time": "2026-03-24T13:34:02.138007Z",
      "orderId": "bb896850-9b35-49af-8683-098b147c2f9f"
    },
    {
      "action": "BUY",
      "ticker": "OSUR",
      "qty": 14,
      "price": 3.2,
      "date": "2026-03-24",
      "time": "2026-03-24T13:33:47.521851Z",
      "orderId": "4f002bd1-2ecc-434c-9944-f3ee70ea912e"
    },
    {
      "action": "BUY",
      "ticker": "AHCO",
      "qty": 23,
      "price": 10.79,
      "date": "2026-03-24",
      "time": "2026-03-24T13:33:46.781436Z",
      "orderId": "5db006cf-4b83-4253-b2d1-3db517eb396c"
    },
    {
      "action": "BUY",
      "ticker": "OSUR",
      "qty": 30,
      "price": 3.2,
      "date": "2026-03-24",
      "time": "2026-03-24T13:33:38.079947Z",
      "orderId": "bb896850-9b35-49af-8683-098b147c2f9f"
    },
    {
      "action": "BUY",
      "ticker": "OSUR",
      "qty": 76,
      "price": 3.16,
      "date": "2026-03-24",
      "time": "2026-03-24T13:32:59.376899Z",
      "orderId": "bb896850-9b35-49af-8683-098b147c2f9f"
    },
    {
      "action": "BUY",
      "ticker": "FIVE",
      "qty": 1,
      "price": 229.36,
      "date": "2026-03-24",
      "time": "2026-03-24T13:32:44.611906Z",
      "orderId": "46a9e3d0-cedf-4b28-ab41-e2e844648eef"
    },
    {
      "action": "BUY",
      "ticker": "MKTW",
      "qty": 38,
      "price": 15.49,
      "date": "2026-03-24",
      "time": "2026-03-24T13:32:22.445378Z",
      "orderId": "4aaab841-d237-45c3-b8bf-1eb80301fc05"
    },
    {
      "action": "BUY",
      "ticker": "OSUR",
      "qty": 116,
      "price": 3.18,
      "date": "2026-03-24",
      "time": "2026-03-24T13:32:16.897055Z",
      "orderId": "4f002bd1-2ecc-434c-9944-f3ee70ea912e"
    },
    {
      "action": "BUY",
      "ticker": "AHCO",
      "qty": 19,
      "price": 10.61,
      "date": "2026-03-24",
      "time": "2026-03-24T13:32:15.721956Z",
      "orderId": "5db006cf-4b83-4253-b2d1-3db517eb396c"
    },
    {
      "action": "BUY",
      "ticker": "FIVE",
      "qty": 4,
      "price": 229.36,
      "date": "2026-03-24",
      "time": "2026-03-24T13:32:09.012986Z",
      "orderId": "46a9e3d0-cedf-4b28-ab41-e2e844648eef"
    },
    {
      "action": "BUY",
      "ticker": "SFM",
      "qty": 15,
      "price": 79.46,
      "date": "2026-03-24",
      "time": "2026-03-24T13:32:04.979177Z",
      "orderId": "a44ef0c1-2937-4c43-a5d3-9279582d471d"
    },
    {
      "action": "SELL",
      "ticker": "WULF260410C00015000",
      "qty": 3,
      "price": 1.99,
      "date": "2026-03-24",
      "time": "2026-03-24T13:31:52.917471Z",
      "orderId": "6399fd21-db57-42a9-8123-5fb007beeb5e"
    },
    {
      "action": "SELL",
      "ticker": "WULF260410C00015000",
      "qty": 7,
      "price": 1.99,
      "date": "2026-03-24",
      "time": "2026-03-24T13:31:52.806745Z",
      "orderId": "6399fd21-db57-42a9-8123-5fb007beeb5e"
    },
    {
      "action": "BUY",
      "ticker": "MKTW",
      "qty": 30,
      "price": 15.49,
      "date": "2026-03-24",
      "time": "2026-03-24T13:31:38.420662Z",
      "orderId": "4aaab841-d237-45c3-b8bf-1eb80301fc05"
    },
    {
      "action": "BUY",
      "ticker": "NVDA260410C00180000",
      "qty": 3,
      "price": 3.5,
      "date": "2026-03-24",
      "time": "2026-03-24T13:31:32.48675Z",
      "orderId": "32889a16-cf68-497e-b795-056281fc389c"
    }
  ],
  "metadata": {
    "lastUpdated": "2026-03-24T16:35:44.593Z",
    "startingCapital": 100000
  },
  "optionsExposure": {
    "portfolioValue": 50679.14,
    "totalOptionsValue": 4843,
    "optionsPct": 9.56,
    "maxAllowedPct": 10,
    "maxAllowedValue": 5067.91,
    "remainingCapacity": 224.91,
    "overLimit": false,
    "nearLimit": true,
    "status": "🟡 NEAR LIMIT",
    "positionCount": 4
  },
  "optionsPositions": [
    {
      "symbol": "NVDA260327C00190000",
      "root": "NVDA",
      "type": "call",
      "strike": 190,
      "expiry": "2026-03-27",
      "qty": 1,
      "marketValue": 3,
      "pctOfPortfolio": 0.01
    },
    {
      "symbol": "NVDA260410C00180000",
      "root": "NVDA",
      "type": "call",
      "strike": 180,
      "expiry": "2026-04-10",
      "qty": 8,
      "marketValue": 2400,
      "pctOfPortfolio": 4.74
    },
    {
      "symbol": "STIM260417C00002500",
      "root": "STIM",
      "type": "call",
      "strike": 2.5,
      "expiry": "2026-04-17",
      "qty": 15,
      "marketValue": 0,
      "pctOfPortfolio": 0
    },
    {
      "symbol": "TSM260417C00350000",
      "root": "TSM",
      "type": "call",
      "strike": 350,
      "expiry": "2026-04-17",
      "qty": 2,
      "marketValue": 2440,
      "pctOfPortfolio": 4.81
    }
  ]
}